analytics/__init__.py
analytics/usage_stats.py
cache/__init__.py
cache/embedding_cache.py
cli/__init__.py
cli/commands/__init__.py
cli/commands/add.py
cli/commands/backup.py
cli/commands/delete.py
cli/commands/export.py
cli/commands/github_gist.py
cli/commands/github_import.py
cli/commands/import_snippets.py
cli/commands/index.py
cli/commands/list_snippets.py
cli/commands/search.py
cli/commands/search_backup.py
cli/commands/show.py
cli/commands/stats.py
cli/commands/update.py
config/__init__.py
config/manager.py
db/__init__.py
db/bootstrap.sql
db/full_text.py
db/migrate.py
db/pool.py
db/queries.py
db/setup.py
db/sqlite_adapter.py
integrations/__init__.py
integrations/github/__init__.py
integrations/github/auth.py
llm/__init__.py
llm/embedding_factory.py
llm/embeddings.py
llm/embeddings_local.py
llm/embeddings_openai.py
llm/query_enhancer.py
llm/summarizer.py
search/__init__.py
search/fuzzy.py
search/hybrid.py
search/ranking.py
search/related.py
snipvault/__init__.py
snipvault/__main__.py
utils/__init__.py
utils/api_tracker.py
utils/code_parser.py
utils/exceptions.py
utils/file_detector.py
utils/ignore_patterns.py
utils/logger.py
utils/pagination.py
utils/performance.py
snipvault-1.0.1.dist-info/METADATA
snipvault-1.0.1.dist-info/WHEEL
snipvault-1.0.1.dist-info/entry_points.txt
snipvault-1.0.1.dist-info/top_level.txt
snipvault-1.0.1.dist-info/RECORD
