Metadata-Version: 2.4
Name: snipvault
Version: 1.0.1
Summary: LLM-Powered Code Snippet Manager with vector search
Home-page: https://github.com/ARTHURFLECK1828/snipvault
Author: SnipVault Team
Author-email: catcharavind18@gmail.com
License: MIT
Project-URL: Homepage, https://github.com/ARTHURFLECK1828/snipvault
Project-URL: Repository, https://github.com/ARTHURFLECK1828/snipvault
Project-URL: Documentation, https://github.com/ARTHURFLECK1828/snipvault#readme
Keywords: code-snippets,llm,vector-search,cli,gemini
Classifier: Development Status :: 4 - Beta
Classifier: Intended Audience :: Developers
Classifier: Topic :: Software Development :: Libraries :: Python Modules
Classifier: License :: OSI Approved :: MIT License
Classifier: Programming Language :: Python :: 3
Classifier: Programming Language :: Python :: 3.9
Classifier: Programming Language :: Python :: 3.10
Classifier: Programming Language :: Python :: 3.11
Classifier: Programming Language :: Python :: 3.12
Requires-Python: >=3.9
Requires-Dist: click>=8.1.7
Requires-Dist: psycopg2-binary>=2.9.9
Requires-Dist: pinecone-client>=3.0.3
Requires-Dist: google-generativeai>=0.3.2
Requires-Dist: python-dotenv>=1.0.0
Requires-Dist: rich>=13.7.0
Requires-Dist: pyperclip>=1.8.2
Requires-Dist: pyyaml>=6.0.1
Provides-Extra: dev
Requires-Dist: pytest>=7.4.3; extra == "dev"
Requires-Dist: pytest-cov>=4.1.0; extra == "dev"
Requires-Dist: pytest-mock>=3.12.0; extra == "dev"
Requires-Dist: pytest-asyncio>=0.23.2; extra == "dev"
Requires-Dist: ruff>=0.1.8; extra == "dev"
Requires-Dist: black>=23.12.1; extra == "dev"
Requires-Dist: mypy>=1.7.1; extra == "dev"
Requires-Dist: pre-commit>=3.6.0; extra == "dev"
Requires-Dist: types-psycopg2>=2.9.21.16; extra == "dev"
Provides-Extra: async
Requires-Dist: aiohttp>=3.9.1; extra == "async"
Requires-Dist: asyncpg>=0.29.0; extra == "async"
Provides-Extra: local-embeddings
Requires-Dist: sentence-transformers>=2.2.2; extra == "local-embeddings"
Requires-Dist: torch>=2.0.0; extra == "local-embeddings"
Provides-Extra: openai
Requires-Dist: openai>=1.3.0; extra == "openai"
Provides-Extra: all
Requires-Dist: snipvault[async,dev,local-embeddings,openai]; extra == "all"
Dynamic: author-email
Dynamic: home-page
Dynamic: requires-python
